fishjam/__init__.py
fishjam/_webhook_notifier.py
fishjam/_ws_notifier.py
fishjam/errors.py
fishjam/types.py
fishjam/utils.py
fishjam/version.py
fishjam/_openapi_client/__init__.py
fishjam/_openapi_client/client.py
fishjam/_openapi_client/errors.py
fishjam/_openapi_client/py.typed
fishjam/_openapi_client/types.py
fishjam/_openapi_client/api/__init__.py
fishjam/_openapi_client/api/room/__init__.py
fishjam/_openapi_client/api/room/add_peer.py
fishjam/_openapi_client/api/room/create_room.py
fishjam/_openapi_client/api/room/delete_peer.py
fishjam/_openapi_client/api/room/delete_room.py
fishjam/_openapi_client/api/room/get_all_rooms.py
fishjam/_openapi_client/api/room/get_room.py
fishjam/_openapi_client/api/room/refresh_token.py
fishjam/_openapi_client/api/room/subscribe_peer.py
fishjam/_openapi_client/api/room/subscribe_tracks.py
fishjam/_openapi_client/api/stream/__init__.py
fishjam/_openapi_client/api/stream/create_stream.py
fishjam/_openapi_client/api/stream/delete_stream.py
fishjam/_openapi_client/api/stream/get_all_streams.py
fishjam/_openapi_client/api/stream/get_stream.py
fishjam/_openapi_client/api/streamer/__init__.py
fishjam/_openapi_client/api/streamer/create_streamer.py
fishjam/_openapi_client/api/streamer/delete_streamer.py
fishjam/_openapi_client/api/streamer/generate_streamer_token.py
fishjam/_openapi_client/api/viewer/__init__.py
fishjam/_openapi_client/api/viewer/create_viewer.py
fishjam/_openapi_client/api/viewer/delete_viewer.py
fishjam/_openapi_client/api/viewer/generate_viewer_token.py
fishjam/_openapi_client/models/__init__.py
fishjam/_openapi_client/models/add_peer_body.py
fishjam/_openapi_client/models/agent_output.py
fishjam/_openapi_client/models/audio_format.py
fishjam/_openapi_client/models/audio_sample_rate.py
fishjam/_openapi_client/models/error.py
fishjam/_openapi_client/models/peer.py
fishjam/_openapi_client/models/peer_details_response.py
fishjam/_openapi_client/models/peer_details_response_data.py
fishjam_server_sdk-0.24.0.dist-info/METADATA
fishjam_server_sdk-0.24.0.dist-info/WHEEL
fishjam_server_sdk-0.24.0.dist-info/entry_points.txt
fishjam_server_sdk-0.24.0.dist-info/licenses/LICENSE
fishjam_server_sdk-0.24.0.dist-info/RECORD
