Metadata-Version: 2.4
Name: fishjam-server-sdk
Version: 0.24.0
Summary: Python server SDK for the Fishjam
Project-URL: Homepage, https://github.com/fishjam-cloud/python-server-sdk
Project-URL: Documentation, https://fishjam-cloud.github.io/python-server-sdk/fishjam
Author-email: Fishjam Team <contact@fishjam.io>
License-Expression: Apache-2.0
License-File: LICENSE
Requires-Python: >=3.11
Requires-Dist: aenum<4,>=3.1.15
Requires-Dist: attrs>=21.3.0
Requires-Dist: betterproto==2.0.0b6
Requires-Dist: flask-cors<7,>=6.0.1
Requires-Dist: httpx<0.29.0,>=0.28.0
Requires-Dist: python-dateutil<3,>=2.8.2
Requires-Dist: urllib3<2,>=1.25.3
Requires-Dist: websockets~=15.0
Provides-Extra: gemini
Requires-Dist: google-genai>=1.43.0; extra == 'gemini'
